[
    {
        "author": "2 Mż 15,11 (BE)",
        "content": "Któż jest jak Ty, wśród bogów, Panie? Któż jest jak Ty, wspaniały w świętości, straszliwy w chwale, czyniący cuda? "
    },
    {
        "author": "1 Kor 8,5-6",
        "content": "Bo chociaż nawet są tak zwani bogowie, czy to na niebie, czy na ziemi, i dlatego jest wielu bogów i wielu panów, wszakże dla nas istnieje tylko jeden Bóg Ojciec, z którego pochodzi wszystko i dla którego istniejemy, i jeden Pan, Jezus Chrystus, przez którego wszystko istnieje i przez którego my także istniejemy."
    },
    {
        "author": "Marcin Luter †1546",
        "content": "To, na czym zawisnęło serce twoje i na czym ono polega, jest właściwie twoim Bogiem."
    }
]