[
    {
        "author": "Ps 116,8",
        "content": "Uchroniłeś duszę moją od śmierci, oczy moje od łez, nogi moje od upadku."
    },
    {
        "author": "Łk 8,43-44 (BE)",
        "content": "Kobieta, która od dwunastu lat miała krwotok i cały swój majątek wydała na lekarzy, a żaden nie zdołał jej pomóc. Gdy podeszła od tyłu i dotknęła skraju Jego płaszcza, zaraz ustał jej krwotok. "
    },
    {
        "author": "ks. Dietrich Bonhoeffer †1945",
        "content": "W codziennym życiu prawie nie zdajemy sobie sprawy, że otrzymujemy znacznie więcej niż dajemy i że tylko dzięki wdzięczności życie staje się bogate."
    }
]