[
    {
        "author": "Iz 43,24-25",
        "content": "Obciążyłeś mnie swoimi grzechami, utrudziłeś mnie swoimi przewinieniami. Ja, jedynie Ja, mogę przez wzgląd na siebie zmazać twoje przestępstwa i twoich grzechów nie wspomnę."
    },
    {
        "author": "J  5,17",
        "content": "Jezus odpowiedział im: Mój Ojciec aż dotąd działa i Ja działam. "
    },
    {
        "author": "modlitwa z Zimbabwe",
        "content": "Wyznajemy nasze naganne postępowanie i prosimy o odwagę, by się zmienić. Przebacz nam w swojej łasce i wysłuchaj naszej modlitwy. "
    }
]