[
    {
        "author": "Ps 119,67",
        "content": "Zanim zostałem upokorzony, błądziłem, ale teraz strzegę twego słowa. "
    },
    {
        "author": "J 21,16",
        "content": "Rzecze mu Jezus znowu po raz drugi: Szymonie, synu Jana, miłujesz mnie? Rzecze mu: Tak, Panie! Ty wiesz, że cię miłuję. Rzekł mu: Paś owieczki moje."
    },
    {
        "author": "Wilhelm von Saint-Thierry †1148",
        "content": "Gdybyście mnie dzisiaj zapytali, tak jak Jezus zapytał Piotra: „Czy mnie kochasz?”, nie odważyłbym się odpowiedzieć: „Wiesz, że cię kocham”. Ale ze szczęśliwym i spokojnym sumieniem mógłbym powiedzieć: „Wiesz, że chcę cię kochać”. "
    }
]