[
    {
        "author": "Ps 37,4 (BE)",
        "content": "Raduj się w Panu, On spełni pragnienia twego serca. "
    },
    {
        "author": "Mt 7,11",
        "content": "Jeśli tedy wy, będąc złymi, potraficie dawać dobre dary dzieciom swoim, o ileż więcej Ojciec wasz, który jest w niebie, da dobre rzeczy tym, którzy go proszą."
    },
    {
        "author": "ŚE 480,2; Franciszek Karpiński †1825",
        "content": "A człowiek, który bez miary, obsypany Twymi dary, coś go stworzył i ocalił, a czemuż by Cię nie chwalił?"
    }
]